doc_parse_convert/__init__.py
doc_parse_convert/config.py
doc_parse_convert/exceptions.py
doc_parse_convert/ai/__init__.py
doc_parse_convert/ai/client.py
doc_parse_convert/ai/prompts.py
doc_parse_convert/ai/schemas.py
doc_parse_convert/conversion/__init__.py
doc_parse_convert/conversion/epub.py
doc_parse_convert/conversion/html.py
doc_parse_convert/conversion/storage.py
doc_parse_convert/extraction/__init__.py
doc_parse_convert/extraction/base.py
doc_parse_convert/extraction/pdf.py
doc_parse_convert/extraction/structure.py
doc_parse_convert/image_extraction/__init__.py
doc_parse_convert/image_extraction/extractor.py
doc_parse_convert/image_extraction/image_types.py
doc_parse_convert/image_extraction/prompts.py
doc_parse_convert/image_extraction/schemas.py
doc_parse_convert/models/__init__.py
doc_parse_convert/models/content.py
doc_parse_convert/models/document.py
doc_parse_convert/utils/__init__.py
doc_parse_convert/utils/factory.py
doc_parse_convert/utils/image.py
doc_parse_convert/utils/io_helpers.py
doc_parse_convert/utils/validators.py
doc_parse_convert-0.6.1.dist-info/licenses/LICENSE
doc_parse_convert-0.6.1.dist-info/METADATA
doc_parse_convert-0.6.1.dist-info/WHEEL
doc_parse_convert-0.6.1.dist-info/top_level.txt
doc_parse_convert-0.6.1.dist-info/RECORD
