Metadata-Version: 2.4
Name: doc_parse_convert
Version: 0.6.1
Summary: Utilities for document content extraction and conversion
Author: Guthman
Classifier: Programming Language :: Python :: 3
Classifier: License :: OSI Approved :: MIT License
Classifier: Operating System :: OS Independent
Requires-Python: >=3.7
License-File: LICENSE
Requires-Dist: google-cloud-aiplatform<2.0.0,>=1.86.0
Requires-Dist: pymupdf<2.0.0,>=1.19.0
Requires-Dist: google-api-core<3.0.0,>=2.0.0
Requires-Dist: google-auth<3.0.0,>=2.0.0
Requires-Dist: google-auth-oauthlib<2.0.0,>=0.4.0
Requires-Dist: pillow<13.0.0,>=9.0.0
Requires-Dist: tenacity<10.0.0,>=8.0.0
Requires-Dist: ebooklib<1.0.0,>=0.17.0
Requires-Dist: beautifulsoup4<5.0.0,>=4.9.0
Requires-Dist: requests<3.0.0,>=2.25.0
Dynamic: author
Dynamic: classifier
Dynamic: description
Dynamic: description-content-type
Dynamic: license-file
Dynamic: requires-dist
Dynamic: requires-python
Dynamic: summary
